d1_onedrive/__init__.py
d1_onedrive/onedrive.py
d1_onedrive/impl/__init__.py
d1_onedrive/impl/attributes.py
d1_onedrive/impl/cache_memory.py
d1_onedrive/impl/directory.py
d1_onedrive/impl/disk_cache.py
d1_onedrive/impl/log_decorator.py
d1_onedrive/impl/object_tree.py
d1_onedrive/impl/onedrive_exceptions.py
d1_onedrive/impl/os_escape.py
d1_onedrive/impl/util.py
d1_onedrive/impl/assets/d1.icon
d1_onedrive/impl/clients/__init__.py
d1_onedrive/impl/clients/onedrive_d1_client.py
d1_onedrive/impl/clients/onedrive_solr_client.py
d1_onedrive/impl/clients/onedrive_zotero_client.py
d1_onedrive/impl/clients/query_engine_description.py
d1_onedrive/impl/drivers/__init__.py
d1_onedrive/impl/drivers/dokan/__init__.py
d1_onedrive/impl/drivers/dokan/const.py
d1_onedrive/impl/drivers/dokan/d1_dokan.py
d1_onedrive/impl/drivers/dokan/dokan.py
d1_onedrive/impl/drivers/dokan/fs_util.py
d1_onedrive/impl/drivers/dokan/solrclient.py
d1_onedrive/impl/drivers/fuse/__init__.py
d1_onedrive/impl/drivers/fuse/callbacks.py
d1_onedrive/impl/drivers/fuse/d1_fuse.py
d1_onedrive/impl/resolver/__init__.py
d1_onedrive/impl/resolver/author.py
d1_onedrive/impl/resolver/d1_object.py
d1_onedrive/impl/resolver/flat_space.py
d1_onedrive/impl/resolver/object_tree_resolver.py
d1_onedrive/impl/resolver/region.py
d1_onedrive/impl/resolver/resolver_base.py
d1_onedrive/impl/resolver/resource_map.py
d1_onedrive/impl/resolver/root.py
d1_onedrive/impl/resolver/single.py
d1_onedrive/impl/resolver/taxa.py
d1_onedrive/impl/resolver/time_period.py
d1_onedrive/impl/tests/__init__.py
d1_onedrive/impl/tests/command_echoer.py
d1_onedrive/impl/tests/object_tree_test_sample.py
d1_onedrive/impl/tests/test_author_resolver.py
d1_onedrive/impl/tests/test_d1_object_resolver.py
d1_onedrive/impl/tests/test_disk_cache.py
d1_onedrive/impl/tests/test_flat_space_resolver.py
d1_onedrive/impl/tests/test_os_escape.py
d1_onedrive/impl/tests/test_region_resolver.py
d1_onedrive/impl/tests/test_resource_map_resolver.py
dataone.onedrive-3.5.2.dist-info/METADATA
dataone.onedrive-3.5.2.dist-info/WHEEL
dataone.onedrive-3.5.2.dist-info/top_level.txt
dataone.onedrive-3.5.2.dist-info/RECORD
